LICENSE.txt
MANIFEST.in
README.rst
setup.cfg
setup.py
edimdownloader.egg-info/PKG-INFO
edimdownloader.egg-info/SOURCES.txt
edimdownloader.egg-info/dependency_links.txt
edimdownloader.egg-info/entry_points.txt
edimdownloader.egg-info/requires.txt
edimdownloader.egg-info/top_level.txt
edimensionpkg/__init__.py
edimensionpkg/__main__.py
edimensionpkg/edimdownloader.py
edimensionpkg/utilities.py