Metadata-Version: 1.1
Name: edimdownloader
Version: 1.1.1
Summary: A downloader for Edimension
Home-page: https://github.com/ongteckwu/edimdownloader
Author: Ong Teck Wu
Author-email: teckwu_ong@mymail.sutd.edu.sg
License: MIT
Keywords: sutd edimension
Platform: UNKNOWN
Classifier: License :: OSI Approved :: MIT License
Classifier: Programming Language :: Python :: 2.6
Classifier: Programming Language :: Python :: 2.7
Classifier: Programming Language :: Python :: 3.2
Classifier: Programming Language :: Python :: 3.3
Classifier: Programming Language :: Python :: 3.4
Classifier: Programming Language :: Python :: 3.5
